outros/0303/AluSeq.v

module AluSeq(
  input clk, 
  input [7:0] a, 
  input [7:0] b, 
  input [1:0] op, 
  output [7:0] c);

  reg [7:0] c_reg;
  assign c = c_reg;

  always @(posedge clk) begin     //@(posedge) == borda de subida
    case (op)
      0: c_reg <= a + b;
      1: c_reg <= a - b;
      2: c_reg <= a & b;
      3: c_reg <= a | b;
      default: c_reg <= 0;
    endcase
  end

endmodule

module test(output v);

  reg clk;
  always #3 clk <= ~clk;

  reg [7:0] a;
  reg [7:0] b;
  reg [1:0] op;

  wire [7:0] c;

  AluSeq A(clk, a, b, op, c);


  initial begin
    $dumpvars(0, A);
    #2;
    clk <= 0;
    #10;
    a <= 7;
    b <= 3;
    op <= 0;
    #20;
    op <= 1;
    #30;
    op <= 2;
    #40;
    op <= 3;
    #50;
    op <= 0;
    #500;
    $finish;
  end
endmodule

outros/0303/dump.vcd
$date
	Thu Mar  3 21:21:25 2016
$end
$version
	Icarus Verilog
$end
$timescale
	1s
$end
$scope module test $end
$scope module A $end
$var wire 8 ! a [7:0] $end
$var wire 8 " b [7:0] $end
$var wire 8 # c [7:0] $end
$var wire 1 $ clk $end
$var wire 2 % op [1:0] $end
$var reg 8 & c_reg [7:0] $end
$upscope $end
$upscope $end
$enddefinitions $end
#0
$dumpvars
bx &
bx %
x$
bx #
bx "
bx !
$end
#2
0$
#3
b0 &
b0 #
1$
#6
0$
#9
1$
#12
0$
b0 %
b11 "
b111 !
#15
b1010 &
b1010 #
1$
#18
0$
#21
1$
#24
0$
#27
1$
#30
0$
#32
b1 %
#33
b100 &
b100 #
1$
#36
0$
#39
1$
#42
0$
#45
1$
#48
0$
#51
1$
#54
0$
#57
1$
#60
0$
#62
b10 %
#63
b11 &
b11 #
1$
#66
0$
#69
1$
#72
0$
#75
1$
#78
0$
#81
1$
#84
0$
#87
1$
#90
0$
#93
1$
#96
0$
#99
1$
#102
0$
b11 %
#105
b111 &
b111 #
1$
#108
0$
#111
1$
#114
0$
#117
1$
#120
0$
#123
1$
#126
0$
#129
1$
#132
0$
#135
1$
#138
0$
#141
1$
#144
0$
#147
1$
#150
0$
#152
b0 %
#153
b1010 &
b1010 #
1$
